[{"C:\\_MyProgram\\Vocal\\Lingua\\Maestro\\csvRead.py": "ASCII"}, {"C:\\Users\\Tomohiro.Kojima\\Downloads\\Lingua_YarpTextMsg.txt": "ASCII"}, {"C:\\_MyProgram\\Vocal\\Lingua\\Maestro\\test\\yarpClientTest.py": "ASCII"}, {"C:\\_MyProgram\\Vocal\\Lingua\\Maestro\\test\\checkAudioDevicesTest.py": "ASCII"}, {"C:\\_MyProgram\\Vocal\\Lingua\\Maestro\\yarpClient.py": "ASCII"}, {"C:\\_MyProgram\\Vocal\\Lingua\\Maestro\\test\\recAudioTest.py": "ASCII"}, {"C:\\_MyProgram\\Vocal\\Lingua\\Maestro\\yarpClientTest.py": "ASCII"}, {"C:\\_MyProgram\\Vocal\\Noblib\\Robotics\\Activities\\YarpTextMsgServer.cpp": "UTF-8"}, {"C:\\Users\\Tomohiro.Kojima\\Dropbox\\Py\\csvRead.py": "ASCII"}, {"C:\\Users\\Tomohiro.Kojima\\Dropbox\\Py\\yarpClient.py": "ASCII"}, {"C:\\Users\\Tomohiro.Kojima\\Dropbox\\Py\\recAudio.py": "ASCII"}, {"C:\\Users\\Tomohiro.Kojima\\Dropbox\\Py\\yarpClientTest.py": "ASCII"}, {"C:\\Users\\Tomohiro.Kojima\\Dropbox\\Py\\linguaExperiment.py": "ASCII"}, {"C:\\Users\\Tomohiro.Kojima\\Dropbox\\Py\\vtTest.csv": "ASCII"}, {"C:\\Users\\Tomohiro.Kojima\\Dropbox\\Py\\tongueTest.csv": "ASCII"}, {"C:\\_MyProgram\\Vocal\\Noblib\\Robotics\\test\\makeLinguaCtrl.py": "ASCII"}, {"C:\\_MyProgram\\Vocal\\Noblib\\Robotics\\test\\yarp_tcl.sd": "ASCII"}, {"C:\\_MyProgram\\Vocal\\Noblib\\Util\\Curses.hpp": "UTF-8"}, {"C:\\_MyProgram\\Vocal\\Noblib\\LIB\\include\\curses.h": "ASCII"}, {"C:\\_MyProgram\\Vocal\\Noblib\\Robotics\\test\\yarpClient.mk": "ASCII"}, {"C:\\_MyProgram\\Vocal\\Noblib\\Robotics\\test\\yarpClient.cpp": "ASCII"}, {"C:\\Users\\Tomohiro.Kojima\\Documents\\yarpClient.py": "ASCII"}, {"C:\\Users\\Tomohiro.Kojima\\Documents\\sample_.py": "ASCII"}, {"C:\\_MyProgram\\Vocal\\Noblib\\Robotics\\Activities\\YarpTextMsgServer.h": "SHIFT_JIS"}, {"C:\\Users\\Tomohiro.Kojima\\Documents\\csvRead.py": "ASCII"}, {"C:\\Users\\Tomohiro.Kojima\\Documents\\tongueTest.csv": "ASCII"}, {"C:\\Users\\Tomohiro.Kojima\\Documents\\recAndPlay.py": "ASCII"}, {"C:\\Users\\Tomohiro.Kojima\\Documents\\recAudio.py": "ASCII"}, {"C:\\Users\\Tomohiro.Kojima\\AppData\\Roaming\\Sublime Text 2\\Packages\\Default\\Preferences.sublime-settings": "ASCII"}, {"C:\\Users\\Tomohiro.Kojima\\Documents\\sample.py": "ASCII"}, {"C:\\Users\\Tomohiro.Kojima\\Documents\\sample5.py": "ASCII"}, {"C:\\Users\\Tomohiro.Kojima\\Downloads\\00README-ja.txt": "SHIFT_JIS"}, {"C:\\_MyProgram\\Vocal\\Noblib\\Sound\\test\\waveinTest.cpp": "SHIFT_JIS"}, {"C:\\_MyProgram\\Vocal\\Noblib\\Robotics\\Activities\\TongueLimit.h": "ASCII"}, {"C:\\Users\\Tomohiro.Kojima\\Documents\\sample4.py": "UTF-8"}, {"C:\\Users\\Tomohiro.Kojima\\Documents\\sample3.py": "ASCII"}, {"C:\\Users\\Tomohiro.Kojima\\Documents\\client.py": "ASCII"}, {"C:\\Users\\Tomohiro.Kojima\\Documents\\rec_and_play.py": "ASCII"}, {"C:\\Users\\Tomohiro.Kojima\\Documents\\sample2.py": "ASCII"}, {"C:\\Users\\Tomohiro.Kojima\\Anaconda2\\Lib\\site-packages\\matplotlib\\mpl-data\\matplotlibrc": "ASCII"}, {"C:\\_MyProgram\\Vocal\\Noblib\\Robotics\\Activities\\MechanicalProperty.h": "ASCII"}, {"C:\\2015-10-25_CryingCalc\\RecData\\6MoA\\result.txt": "ASCII"}, {"C:\\2015-10-25_CryingCalc\\_Praat\\get_average_formant.praat": "UTF-8"}, {"C:\\2015-10-25_CryingCalc\\RecData\\6MoA\\06m01d-1_hungry_058.wav.txt": "ASCII"}, {"C:\\_MyProgram\\Vocal\\Noblib\\Robotics\\test\\tongueLimitTest.cpp": "ASCII"}, {"C:\\_MyProgram\\Vocal\\Noblib\\Robotics\\test\\linguaCtrl.mk": "ASCII"}, {"C:\\_MyProgram\\Vocal\\Noblib\\Robotics\\test\\linguaCtrl.cpp": "ASCII"}, {"C:\\_MyProgram\\Vocal\\Noblib\\Robotics\\Activity.h": "SHIFT_JIS"}, {"C:\\_MyProgram\\Vocal\\Noblib\\Robotics\\RevoluteJoint.h": "ASCII"}, {"C:\\_MyProgram\\Vocal\\Noblib\\Robotics\\Activities\\TomokiVc.h": "ASCII"}, {"C:\\_MyProgram\\Vocal\\Noblib\\Robotics\\test\\tongueLimitTest.mk": "ASCII"}, {"C:\\_MyProgram\\Vocal\\Noblib\\Robotics\\test\\mechaPropTest.cpp": "ASCII"}, {"C:\\Users\\Tomohiro.Kojima\\Dropbox\\_MyProgram\\Vocal\\Noblib\\Robotics\\Activities\\MechanicalProperty.h": "ASCII"}, {"C:\\_MyProgram\\Vocal\\Noblib\\Util\\DataTypes.h": "ASCII"}, {"C:\\_MyProgram\\Vocal\\Noblib\\Util\\Angle.h": "ASCII"}, {"C:\\_MyProgram\\Vocal\\Noblib\\Robotics\\test\\mechaPropTest.mk": "ASCII"}, {"C:\\_MyProgram\\Vocal\\Noblib\\Robotics\\test\\tongueCfg.h": "ASCII"}, {"C:\\_MyProgram\\Vocal\\Noblib\\Robotics\\JointConfiguration.h": "SHIFT_JIS"}, {"C:\\_MyProgram\\Vocal\\Noblib\\Robotics\\JointConfiguration.cpp": "SHIFT_JIS"}, {"C:\\_MyProgram\\Vocal\\Noblib\\Device\\DeviceConfiguration.h": "UTF-8"}, {"C:\\_MyProgram\\Vocal\\Noblib\\Device\\DeviceConfiguration.cpp": "UTF-8"}, {"C:\\_MyProgram\\Vocal\\Noblib\\Device\\DcMotorConfiguration.cpp": "UTF-8"}, {"C:\\_MyProgram\\Vocal\\Noblib\\Robotics\\test\\jointCfgTest.cpp": "ASCII"}, {"C:\\cygwin64\\usr\\include\\wchar.h": "ASCII"}, {"C:\\Users\\Tomohiro.Kojima\\AppData\\Roaming\\Sublime Text 2\\Packages\\SublimeClang\\SublimeClang.sublime-settings": "ASCII"}, {"C:\\Users\\Tomohiro.Kojima\\AppData\\Roaming\\Sublime Text 2\\Packages\\User\\SublimeClang.sublime-settings": "ASCII"}, {"C:\\2015-10-25_CryingCalc\\AnaData\\3MoA_8000_1000\\03m03d-1_hungry_058_8000_p1000_for.dat": "ASCII"}, {"C:\\_MyProgram\\Vocal\\Noblib\\Device\\test\\cntTest.mk": "ASCII"}, {"C:\\_MyProgram\\Vocal\\Noblib\\Util\\test\\matTest.mk": "ASCII"}, {"C:\\_MyProgram\\Vocal\\Noblib\\Robotics\\test\\jointCfgTest.mk": "ASCII"}, {"C:\\_MyProgram\\Vocal\\Noblib\\Robotics\\test\\mechaPropTest.h": "ASCII"}, {"C:\\_MyProgram\\Vocal\\Noblib\\Util\\test\\matTest.cpp": "ASCII"}, {"C:\\_MyProgram\\Vocal\\Noblib\\Util\\PGFrame.h": "SHIFT_JIS"}, {"C:\\_MyProgram\\Vocal\\WT_Control\\Speak2\\Voice_set.h": "SHIFT_JIS"}, {"C:\\_MyProgram\\Vocal\\WT_Control\\Speak2\\Word_Set.h": "SHIFT_JIS"}, {"C:\\_MyProgram\\Vocal\\WT_Control\\Speak2\\Set_up.h": "SHIFT_JIS"}]